directoryshard/__init__.py
directoryshard/shardeddirectory.py
directoryshard-1.0.dist-info/LICENSE
directoryshard-1.0.dist-info/METADATA
directoryshard-1.0.dist-info/WHEEL
directoryshard-1.0.dist-info/entry_points.txt
directoryshard-1.0.dist-info/top_level.txt
directoryshard-1.0.dist-info/RECORD
