Metadata-Version: 2.1
Name: directoryshard
Version: 1.0
Author-email: Gerard <gweatherby@uchc.edu>, Jon Wedell <wedell@uchc.edu>
License: MIT license
Project-URL: Repository, https://github.com/NMRhub/directoryshard.git
Project-URL: Bug Tracker, https://github.com/NMRhub/directoryshard.git/issues
Classifier: Programming Language :: Python :: 3
Requires-Python: >=3.8
License-File: LICENSE
